langchain_search1api/__init__.py
langchain_search1api/tools.py
langchain_search1api-0.1.0.dist-info/LICENSE
langchain_search1api-0.1.0.dist-info/METADATA
langchain_search1api-0.1.0.dist-info/WHEEL
langchain_search1api-0.1.0.dist-info/top_level.txt
langchain_search1api-0.1.0.dist-info/RECORD
