Metadata-Version: 2.1
Name: langchain-search1api
Version: 0.1.0
Summary: LangChain tools for the search1api service
Home-page: https://github.com/arashbehmand/langchain_search1api
Author: Arash Behmand
Author-email: arashbehmand@gmail.com
Classifier: Development Status :: 3 - Alpha
Classifier: Intended Audience :: Developers
Classifier: License :: OSI Approved :: MIT License
Classifier: Operating System :: OS Independent
Classifier: Programming Language :: Python :: 3
Classifier: Programming Language :: Python :: 3.8
Classifier: Programming Language :: Python :: 3.9
Classifier: Programming Language :: Python :: 3.10
Classifier: Programming Language :: Python :: 3.11
Classifier: Programming Language :: Python :: 3.12
Requires-Python: >=3.8
License-File: LICENSE
Requires-Dist: langchain>=0.2.0
Requires-Dist: requests>=2.25.0
Requires-Dist: pydantic>=2.5.0
